saih_duero_scraping/__init__.py
saih_duero_scraping/data_downloader.py
saih_duero_scraping/gauging.py
saih_duero_scraping/gauging_collection.py
saih_duero_scraping/gauging_enum.py
saih_duero_scraping/hydrologic_url.py
saih_duero_scraping/hydrologic_years.py
saih_duero_scraping/summary_info_file.py
saih_duero_scraping-1.0.6.dist-info/METADATA
saih_duero_scraping-1.0.6.dist-info/WHEEL
saih_duero_scraping-1.0.6.dist-info/licenses/LICENSE
saih_duero_scraping-1.0.6.dist-info/RECORD
