Metadata-Version: 2.1
Name: saih-duero-scraping
Version: 1.0.6
Summary: Python package for web scraping operations over Saih Duero web page. 
Project-URL: Homepage, https://github.com/jke94/saih-duero-scraping
Project-URL: Bug Tracker, https://github.com/jke94/saih-duero-scraping/issues
Author: Javier Carracedo
License: MIT License
License-File: LICENSE
Classifier: License :: OSI Approved :: MIT License
Classifier: Operating System :: OS Independent
Classifier: Programming Language :: Python :: 3
Requires-Python: >=3.10
